rawpy/enhance.py
rawpy/__init__.py
rawpy/_version.py
rawpy/_rawpy.cpython-311-x86_64-linux-gnu.so
newrawpy.libs/libjasper-1de4fc75.so.4.0.0
newrawpy.libs/libgomp-a34b3233.so.1.0.0
newrawpy.libs/libraw_r-d8e0001f.so.23.0.0
newrawpy.libs/liblcms2-1754e5ba.so.2.0.10
newrawpy.libs/libjpeg-ba92ed0a.so.9.4.0
newrawpy-0.20.0.dist-info/LICENSE
newrawpy-0.20.0.dist-info/LICENSE.LibRaw
newrawpy-0.20.0.dist-info/METADATA
newrawpy-0.20.0.dist-info/RECORD
newrawpy-0.20.0.dist-info/top_level.txt
newrawpy-0.20.0.dist-info/WHEEL
