Metadata-Version: 2.1
Name: newrawpy
Version: 0.20.0
Summary: RAW image processing for Python, a wrapper for libraw
Home-page: https://github.com/shade-labs/newrawpy
Author: Shade
Classifier: Development Status :: 4 - Beta
Classifier: Intended Audience :: Developers
Classifier: Natural Language :: English
Classifier: License :: OSI Approved :: MIT License
Classifier: Programming Language :: Cython
Classifier: Programming Language :: Python :: 3
Classifier: Operating System :: MacOS
Classifier: Operating System :: Microsoft :: Windows
Classifier: Operating System :: POSIX
Classifier: Operating System :: Unix
Classifier: Topic :: Multimedia :: Graphics
Classifier: Topic :: Software Development :: Libraries
License-File: LICENSE
License-File: LICENSE.LibRaw
Requires-Dist: numpy
